Metadata-Version: 1.1
Name: MedusaTest
Version: 0.0.1
Summary: A very test
Home-page: UNKNOWN
Author: Invisible Medusa
Author-email: invisiblemedusa10@gmail.com
License: MIT
Keywords: calculator
Platform: UNKNOWN
Classifier: Development Status :: 5 - Production/Stable
Classifier: Intended Audience :: Education
Classifier: Operating System :: Microsoft :: Windows :: Windows 10
Classifier: License :: OSI Approved :: MIT License
Classifier: Programming Language :: Python :: 3
